src/b3od/__init__.py
src/b3od/meta.py
src/b3od/scrapper.py
src/b3od/utils.py
b3_open_data-1.0.4.dist-info/METADATA
b3_open_data-1.0.4.dist-info/WHEEL
b3_open_data-1.0.4.dist-info/licenses/LICENSE
b3_open_data-1.0.4.dist-info/RECORD
