Metadata-Version: 2.1
Name: b3-open-data
Version: 1.0.4
Summary: Data extractor for the Brazilian Stock Exchange (B3)
Project-URL: homepage, https://github.com/rafaelelter/b3-open-data
Author-email: Rafael Elter <rafaelelter@gmail.com>
License: MIT License
License-File: LICENSE
Keywords: b3,scrapper
Classifier: License :: OSI Approved :: MIT License
Classifier: Operating System :: OS Independent
Classifier: Programming Language :: Python :: 3
Requires-Python: >=3.8
Requires-Dist: pandas>=1.4
Requires-Dist: requests
Provides-Extra: dev
Requires-Dist: black; extra == 'dev'
Requires-Dist: bumpver; extra == 'dev'
Requires-Dist: pytest; extra == 'dev'
